pytools4windows/__init__.py
pytools4windows/pt4winstaller.py
pytools4windows/commandmenu/__include__.txt
pytools4windows/commandmenu/__init__.py
pytools4windows/commandmenu/commandmenu.py
pytools4windows/commandmenu/jsons/Python.json
pytools4windows/commandmenu/jsons/git.json
pytools4windows/commandmenu/jsons/pip.json
pytools4windows/commandmenu/jsons/twine.json
pytools4windows/pathmenu/__init__.py
pytools4windows/pathmenu/pathmenu.py
pytools4windows/pyinstallermenu/__init__.py
pytools4windows/pyinstallermenu/pyinstallermenu.py
pytools4windows-0.1.151.dist-info/METADATA
pytools4windows-0.1.151.dist-info/WHEEL
pytools4windows-0.1.151.dist-info/top_level.txt
pytools4windows-0.1.151.dist-info/RECORD
