Metadata-Version: 2.1
Name: pytools4windows
Version: 0.1.151
Summary: Command line tools for Windows
Home-page: https://github.com/Casey-Litmer/PyTools4Windows
Author: Casey Litmer
Author-email: litmerc@msn.com
License: MIT
Classifier: License :: OSI Approved :: MIT License
Classifier: Programming Language :: Python :: 3
Classifier: Operating System :: OS Independent
Requires-Python: >=3.6
Requires-Dist: macrolibs
Requires-Dist: menucmd
